tacoq/__init__.py
tacoq/core/encoding/__init__.py
tacoq/core/encoding/json_dict.py
tacoq/core/encoding/models.py
tacoq/core/encoding/passthrough.py
tacoq/core/encoding/polymorphic.py
tacoq/core/encoding/pydantic.py
tacoq/core/encoding/string.py
tacoq/core/infra/broker/__init__.py
tacoq/core/infra/broker/client.py
tacoq/core/infra/broker/config.py
tacoq/core/models/__init__.py
tacoq/core/models/avro_serializable_base_model.py
tacoq/core/models/exception.py
tacoq/core/models/task.py
tacoq/core/models/task_assignment_update.py
tacoq/core/models/task_completed_update.py
tacoq/core/models/task_running_update.py
tacoq/core/models/schemas/avro/task.json
tacoq/core/models/schemas/avro/task_assignment_update.json
tacoq/core/models/schemas/avro/task_completed_update.json
tacoq/core/models/schemas/avro/task_running_update.json
tacoq/core/telemetry/__init__.py
tacoq/core/telemetry/logger_manager.py
tacoq/core/telemetry/tracer_manager.py
tacoq/publisher/__init__.py
tacoq/publisher/client.py
tacoq/relay/__init__.py
tacoq/relay/client.py
tacoq/relay/config.py
tacoq/worker/__init__.py
tacoq/worker/client.py
tacoq/worker/config.py
tacoq/worker/cli/__init__.py
tacoq/worker/cli/cli.py
tacoq/worker/cli/importer.py
tacoq/worker/cli/logger.py
tacoq/worker/cli/reloader.py
tacoq/worker/cli/runner.py
tacoq-0.4.0.dist-info/METADATA
tacoq-0.4.0.dist-info/WHEEL
tacoq-0.4.0.dist-info/entry_points.txt
tacoq-0.4.0.dist-info/top_level.txt
tacoq-0.4.0.dist-info/RECORD
