Metadata-Version: 2.4
Name: tacoq
Version: 0.4.0
Summary: Python SDK to interact with the TacoQ task queue.
Author: Manuel Costa, Pedro Ribeiro
Classifier: Programming Language :: Python :: 3
Classifier: Operating System :: OS Independent
Requires-Python: >=3.12
Requires-Dist: aio-pika>=9.5.3
Requires-Dist: aiohttp-retry>=2.9.1
Requires-Dist: aiohttp>=3.11.8
Requires-Dist: aioresponses>=0.7.8
Requires-Dist: click>=8.1.7
Requires-Dist: fastavro>=1.10.0
Requires-Dist: opentelemetry-api>=1.30.0
Requires-Dist: pydantic>=2.10.5
Requires-Dist: tenacity>=9.0.0
Requires-Dist: uuid>=1.30
Requires-Dist: watchfiles>=1.0.3
